<network>
	<name>limited</name>
	<uuid>b329ce1e-5fda-409d-8aa8-03a9cd38e389</uuid>
	<!-- <forward mode='nat'/> -->
	<bridge name='virbr1' stp='on' delay='0'/>
	<mac address='52:54:00:12:fe:02'/>
	<ip address='192.168.13.1' netmask='255.255.255.0'>
		<dhcp>
			<range start='192.168.13.2' end='192.168.13.254'/>
			<host mac='52:54:00:a0:cc:02' name='VM2' ip='192.168.13.2'/>
			<host mac='52:54:00:a0:cc:03' name='VM3' ip='192.168.13.3'/>
			<host mac='52:54:00:a0:cc:04' name='VM4' ip='192.168.13.4'/>
			<host mac='52:54:00:a0:cc:05' name='VM5' ip='192.168.13.5'/>
			<host mac='52:54:00:a0:cc:06' name='VM6' ip='192.168.13.6'/>
			<host mac='52:54:00:a0:cc:07' name='VM7' ip='192.168.13.7'/>
			<host mac='52:54:00:a0:cc:08' name='VM8' ip='192.168.13.8'/>
			<host mac='52:54:00:a0:cc:09' name='VM9' ip='192.168.13.9'/>
			<host mac='52:54:00:a0:cc:0a' name='VM10' ip='192.168.13.10'/>
			<host mac='52:54:00:a0:cc:0b' name='VM11' ip='192.168.13.11'/>
			<host mac='52:54:00:a0:cc:0c' name='VM12' ip='192.168.13.12'/>
			<host mac='52:54:00:a0:cc:0d' name='VM13' ip='192.168.13.13'/>
			<host mac='52:54:00:a0:cc:0e' name='VM14' ip='192.168.13.14'/>
			<host mac='52:54:00:a0:cc:0f' name='VM15' ip='192.168.13.15'/>
			<host mac='52:54:00:a0:cc:10' name='VM16' ip='192.168.13.16'/>
			<host mac='52:54:00:a0:cc:11' name='VM17' ip='192.168.13.17'/>
			<host mac='52:54:00:a0:cc:12' name='VM18' ip='192.168.13.18'/>
			<host mac='52:54:00:a0:cc:13' name='VM19' ip='192.168.13.19'/>
			<host mac='52:54:00:a0:cc:14' name='VM20' ip='192.168.13.20'/>
			<host mac='52:54:00:a0:cc:15' name='VM21' ip='192.168.13.21'/>
			<host mac='52:54:00:a0:cc:16' name='VM22' ip='192.168.13.22'/>
			<host mac='52:54:00:a0:cc:17' name='VM23' ip='192.168.13.23'/>
			<host mac='52:54:00:a0:cc:18' name='VM24' ip='192.168.13.24'/>
			<host mac='52:54:00:a0:cc:19' name='VM25' ip='192.168.13.25'/>
			<host mac='52:54:00:a0:cc:1a' name='VM26' ip='192.168.13.26'/>
			<host mac='52:54:00:a0:cc:1b' name='VM27' ip='192.168.13.27'/>
			<host mac='52:54:00:a0:cc:1c' name='VM28' ip='192.168.13.28'/>
			<host mac='52:54:00:a0:cc:1d' name='VM29' ip='192.168.13.29'/>
			<host mac='52:54:00:a0:cc:1e' name='VM30' ip='192.168.13.30'/>
			<host mac='52:54:00:a0:cc:1f' name='VM31' ip='192.168.13.31'/>
			<host mac='52:54:00:a0:cc:20' name='VM32' ip='192.168.13.32'/>
			<host mac='52:54:00:a0:cc:21' name='VM33' ip='192.168.13.33'/>
			<host mac='52:54:00:a0:cc:22' name='VM34' ip='192.168.13.34'/>
			<host mac='52:54:00:a0:cc:23' name='VM35' ip='192.168.13.35'/>
			<host mac='52:54:00:a0:cc:24' name='VM36' ip='192.168.13.36'/>
			<host mac='52:54:00:a0:cc:25' name='VM37' ip='192.168.13.37'/>
			<host mac='52:54:00:a0:cc:26' name='VM38' ip='192.168.13.38'/>
			<host mac='52:54:00:a0:cc:27' name='VM39' ip='192.168.13.39'/>
			<host mac='52:54:00:a0:cc:28' name='VM40' ip='192.168.13.40'/>
			<host mac='52:54:00:a0:cc:29' name='VM41' ip='192.168.13.41'/>
			<host mac='52:54:00:a0:cc:2a' name='VM42' ip='192.168.13.42'/>
			<host mac='52:54:00:a0:cc:2b' name='VM43' ip='192.168.13.43'/>
			<host mac='52:54:00:a0:cc:2c' name='VM44' ip='192.168.13.44'/>
			<host mac='52:54:00:a0:cc:2d' name='VM45' ip='192.168.13.45'/>
			<host mac='52:54:00:a0:cc:2e' name='VM46' ip='192.168.13.46'/>
			<host mac='52:54:00:a0:cc:2f' name='VM47' ip='192.168.13.47'/>
			<host mac='52:54:00:a0:cc:30' name='VM48' ip='192.168.13.48'/>
			<host mac='52:54:00:a0:cc:31' name='VM49' ip='192.168.13.49'/>
			<host mac='52:54:00:a0:cc:32' name='VM50' ip='192.168.13.50'/>
			<host mac='52:54:00:a0:cc:33' name='VM51' ip='192.168.13.51'/>
			<host mac='52:54:00:a0:cc:34' name='VM52' ip='192.168.13.52'/>
			<host mac='52:54:00:a0:cc:35' name='VM53' ip='192.168.13.53'/>
			<host mac='52:54:00:a0:cc:36' name='VM54' ip='192.168.13.54'/>
			<host mac='52:54:00:a0:cc:37' name='VM55' ip='192.168.13.55'/>
			<host mac='52:54:00:a0:cc:38' name='VM56' ip='192.168.13.56'/>
			<host mac='52:54:00:a0:cc:39' name='VM57' ip='192.168.13.57'/>
			<host mac='52:54:00:a0:cc:3a' name='VM58' ip='192.168.13.58'/>
			<host mac='52:54:00:a0:cc:3b' name='VM59' ip='192.168.13.59'/>
			<host mac='52:54:00:a0:cc:3c' name='VM60' ip='192.168.13.60'/>
			<host mac='52:54:00:a0:cc:3d' name='VM61' ip='192.168.13.61'/>
			<host mac='52:54:00:a0:cc:3e' name='VM62' ip='192.168.13.62'/>
			<host mac='52:54:00:a0:cc:3f' name='VM63' ip='192.168.13.63'/>
			<host mac='52:54:00:a0:cc:40' name='VM64' ip='192.168.13.64'/>
			<host mac='52:54:00:a0:cc:41' name='VM65' ip='192.168.13.65'/>
			<host mac='52:54:00:a0:cc:42' name='VM66' ip='192.168.13.66'/>
			<host mac='52:54:00:a0:cc:43' name='VM67' ip='192.168.13.67'/>
			<host mac='52:54:00:a0:cc:44' name='VM68' ip='192.168.13.68'/>
			<host mac='52:54:00:a0:cc:45' name='VM69' ip='192.168.13.69'/>
			<host mac='52:54:00:a0:cc:46' name='VM70' ip='192.168.13.70'/>
			<host mac='52:54:00:a0:cc:47' name='VM71' ip='192.168.13.71'/>
			<host mac='52:54:00:a0:cc:48' name='VM72' ip='192.168.13.72'/>
			<host mac='52:54:00:a0:cc:49' name='VM73' ip='192.168.13.73'/>
			<host mac='52:54:00:a0:cc:4a' name='VM74' ip='192.168.13.74'/>
			<host mac='52:54:00:a0:cc:4b' name='VM75' ip='192.168.13.75'/>
			<host mac='52:54:00:a0:cc:4c' name='VM76' ip='192.168.13.76'/>
			<host mac='52:54:00:a0:cc:4d' name='VM77' ip='192.168.13.77'/>
			<host mac='52:54:00:a0:cc:4e' name='VM78' ip='192.168.13.78'/>
			<host mac='52:54:00:a0:cc:4f' name='VM79' ip='192.168.13.79'/>
			<host mac='52:54:00:a0:cc:50' name='VM80' ip='192.168.13.80'/>
			<host mac='52:54:00:a0:cc:51' name='VM81' ip='192.168.13.81'/>
			<host mac='52:54:00:a0:cc:52' name='VM82' ip='192.168.13.82'/>
			<host mac='52:54:00:a0:cc:53' name='VM83' ip='192.168.13.83'/>
			<host mac='52:54:00:a0:cc:54' name='VM84' ip='192.168.13.84'/>
			<host mac='52:54:00:a0:cc:55' name='VM85' ip='192.168.13.85'/>
			<host mac='52:54:00:a0:cc:56' name='VM86' ip='192.168.13.86'/>
			<host mac='52:54:00:a0:cc:57' name='VM87' ip='192.168.13.87'/>
			<host mac='52:54:00:a0:cc:58' name='VM88' ip='192.168.13.88'/>
			<host mac='52:54:00:a0:cc:59' name='VM89' ip='192.168.13.89'/>
			<host mac='52:54:00:a0:cc:5a' name='VM90' ip='192.168.13.90'/>
			<host mac='52:54:00:a0:cc:5b' name='VM91' ip='192.168.13.91'/>
			<host mac='52:54:00:a0:cc:5c' name='VM92' ip='192.168.13.92'/>
			<host mac='52:54:00:a0:cc:5d' name='VM93' ip='192.168.13.93'/>
			<host mac='52:54:00:a0:cc:5e' name='VM94' ip='192.168.13.94'/>
			<host mac='52:54:00:a0:cc:5f' name='VM95' ip='192.168.13.95'/>
			<host mac='52:54:00:a0:cc:60' name='VM96' ip='192.168.13.96'/>
			<host mac='52:54:00:a0:cc:61' name='VM97' ip='192.168.13.97'/>
			<host mac='52:54:00:a0:cc:62' name='VM98' ip='192.168.13.98'/>
			<host mac='52:54:00:a0:cc:63' name='VM99' ip='192.168.13.99'/>
			<host mac='52:54:00:a0:cc:64' name='VM100' ip='192.168.13.100'/>
			<host mac='52:54:00:a0:cc:65' name='VM101' ip='192.168.13.101'/>
			<host mac='52:54:00:a0:cc:66' name='VM102' ip='192.168.13.102'/>
			<host mac='52:54:00:a0:cc:67' name='VM103' ip='192.168.13.103'/>
			<host mac='52:54:00:a0:cc:68' name='VM104' ip='192.168.13.104'/>
			<host mac='52:54:00:a0:cc:69' name='VM105' ip='192.168.13.105'/>
			<host mac='52:54:00:a0:cc:6a' name='VM106' ip='192.168.13.106'/>
			<host mac='52:54:00:a0:cc:6b' name='VM107' ip='192.168.13.107'/>
			<host mac='52:54:00:a0:cc:6c' name='VM108' ip='192.168.13.108'/>
			<host mac='52:54:00:a0:cc:6d' name='VM109' ip='192.168.13.109'/>
			<host mac='52:54:00:a0:cc:6e' name='VM110' ip='192.168.13.110'/>
			<host mac='52:54:00:a0:cc:6f' name='VM111' ip='192.168.13.111'/>
			<host mac='52:54:00:a0:cc:70' name='VM112' ip='192.168.13.112'/>
			<host mac='52:54:00:a0:cc:71' name='VM113' ip='192.168.13.113'/>
			<host mac='52:54:00:a0:cc:72' name='VM114' ip='192.168.13.114'/>
			<host mac='52:54:00:a0:cc:73' name='VM115' ip='192.168.13.115'/>
			<host mac='52:54:00:a0:cc:74' name='VM116' ip='192.168.13.116'/>
			<host mac='52:54:00:a0:cc:75' name='VM117' ip='192.168.13.117'/>
			<host mac='52:54:00:a0:cc:76' name='VM118' ip='192.168.13.118'/>
			<host mac='52:54:00:a0:cc:77' name='VM119' ip='192.168.13.119'/>
			<host mac='52:54:00:a0:cc:78' name='VM120' ip='192.168.13.120'/>
			<host mac='52:54:00:a0:cc:79' name='VM121' ip='192.168.13.121'/>
			<host mac='52:54:00:a0:cc:7a' name='VM122' ip='192.168.13.122'/>
			<host mac='52:54:00:a0:cc:7b' name='VM123' ip='192.168.13.123'/>
			<host mac='52:54:00:a0:cc:7c' name='VM124' ip='192.168.13.124'/>
			<host mac='52:54:00:a0:cc:7d' name='VM125' ip='192.168.13.125'/>
			<host mac='52:54:00:a0:cc:7e' name='VM126' ip='192.168.13.126'/>
			<host mac='52:54:00:a0:cc:7f' name='VM127' ip='192.168.13.127'/>
			<host mac='52:54:00:a0:cc:80' name='VM128' ip='192.168.13.128'/>
			<host mac='52:54:00:a0:cc:81' name='VM129' ip='192.168.13.129'/>
			<host mac='52:54:00:a0:cc:82' name='VM130' ip='192.168.13.130'/>
			<host mac='52:54:00:a0:cc:83' name='VM131' ip='192.168.13.131'/>
			<host mac='52:54:00:a0:cc:84' name='VM132' ip='192.168.13.132'/>
			<host mac='52:54:00:a0:cc:85' name='VM133' ip='192.168.13.133'/>
			<host mac='52:54:00:a0:cc:86' name='VM134' ip='192.168.13.134'/>
			<host mac='52:54:00:a0:cc:87' name='VM135' ip='192.168.13.135'/>
			<host mac='52:54:00:a0:cc:88' name='VM136' ip='192.168.13.136'/>
			<host mac='52:54:00:a0:cc:89' name='VM137' ip='192.168.13.137'/>
			<host mac='52:54:00:a0:cc:8a' name='VM138' ip='192.168.13.138'/>
			<host mac='52:54:00:a0:cc:8b' name='VM139' ip='192.168.13.139'/>
			<host mac='52:54:00:a0:cc:8c' name='VM140' ip='192.168.13.140'/>
			<host mac='52:54:00:a0:cc:8d' name='VM141' ip='192.168.13.141'/>
			<host mac='52:54:00:a0:cc:8e' name='VM142' ip='192.168.13.142'/>
			<host mac='52:54:00:a0:cc:8f' name='VM143' ip='192.168.13.143'/>
			<host mac='52:54:00:a0:cc:90' name='VM144' ip='192.168.13.144'/>
			<host mac='52:54:00:a0:cc:91' name='VM145' ip='192.168.13.145'/>
			<host mac='52:54:00:a0:cc:92' name='VM146' ip='192.168.13.146'/>
			<host mac='52:54:00:a0:cc:93' name='VM147' ip='192.168.13.147'/>
			<host mac='52:54:00:a0:cc:94' name='VM148' ip='192.168.13.148'/>
			<host mac='52:54:00:a0:cc:95' name='VM149' ip='192.168.13.149'/>
			<host mac='52:54:00:a0:cc:96' name='VM150' ip='192.168.13.150'/>
			<host mac='52:54:00:a0:cc:97' name='VM151' ip='192.168.13.151'/>
			<host mac='52:54:00:a0:cc:98' name='VM152' ip='192.168.13.152'/>
			<host mac='52:54:00:a0:cc:99' name='VM153' ip='192.168.13.153'/>
			<host mac='52:54:00:a0:cc:9a' name='VM154' ip='192.168.13.154'/>
			<host mac='52:54:00:a0:cc:9b' name='VM155' ip='192.168.13.155'/>
			<host mac='52:54:00:a0:cc:9c' name='VM156' ip='192.168.13.156'/>
			<host mac='52:54:00:a0:cc:9d' name='VM157' ip='192.168.13.157'/>
			<host mac='52:54:00:a0:cc:9e' name='VM158' ip='192.168.13.158'/>
			<host mac='52:54:00:a0:cc:9f' name='VM159' ip='192.168.13.159'/>
			<host mac='52:54:00:a0:cc:a0' name='VM160' ip='192.168.13.160'/>
			<host mac='52:54:00:a0:cc:a1' name='VM161' ip='192.168.13.161'/>
			<host mac='52:54:00:a0:cc:a2' name='VM162' ip='192.168.13.162'/>
			<host mac='52:54:00:a0:cc:a3' name='VM163' ip='192.168.13.163'/>
			<host mac='52:54:00:a0:cc:a4' name='VM164' ip='192.168.13.164'/>
			<host mac='52:54:00:a0:cc:a5' name='VM165' ip='192.168.13.165'/>
			<host mac='52:54:00:a0:cc:a6' name='VM166' ip='192.168.13.166'/>
			<host mac='52:54:00:a0:cc:a7' name='VM167' ip='192.168.13.167'/>
			<host mac='52:54:00:a0:cc:a8' name='VM168' ip='192.168.13.168'/>
			<host mac='52:54:00:a0:cc:a9' name='VM169' ip='192.168.13.169'/>
			<host mac='52:54:00:a0:cc:aa' name='VM170' ip='192.168.13.170'/>
			<host mac='52:54:00:a0:cc:ab' name='VM171' ip='192.168.13.171'/>
			<host mac='52:54:00:a0:cc:ac' name='VM172' ip='192.168.13.172'/>
			<host mac='52:54:00:a0:cc:ad' name='VM173' ip='192.168.13.173'/>
			<host mac='52:54:00:a0:cc:ae' name='VM174' ip='192.168.13.174'/>
			<host mac='52:54:00:a0:cc:af' name='VM175' ip='192.168.13.175'/>
			<host mac='52:54:00:a0:cc:b0' name='VM176' ip='192.168.13.176'/>
			<host mac='52:54:00:a0:cc:b1' name='VM177' ip='192.168.13.177'/>
			<host mac='52:54:00:a0:cc:b2' name='VM178' ip='192.168.13.178'/>
			<host mac='52:54:00:a0:cc:b3' name='VM179' ip='192.168.13.179'/>
			<host mac='52:54:00:a0:cc:b4' name='VM180' ip='192.168.13.180'/>
			<host mac='52:54:00:a0:cc:b5' name='VM181' ip='192.168.13.181'/>
			<host mac='52:54:00:a0:cc:b6' name='VM182' ip='192.168.13.182'/>
			<host mac='52:54:00:a0:cc:b7' name='VM183' ip='192.168.13.183'/>
			<host mac='52:54:00:a0:cc:b8' name='VM184' ip='192.168.13.184'/>
			<host mac='52:54:00:a0:cc:b9' name='VM185' ip='192.168.13.185'/>
			<host mac='52:54:00:a0:cc:ba' name='VM186' ip='192.168.13.186'/>
			<host mac='52:54:00:a0:cc:bb' name='VM187' ip='192.168.13.187'/>
			<host mac='52:54:00:a0:cc:bc' name='VM188' ip='192.168.13.188'/>
			<host mac='52:54:00:a0:cc:bd' name='VM189' ip='192.168.13.189'/>
			<host mac='52:54:00:a0:cc:be' name='VM190' ip='192.168.13.190'/>
			<host mac='52:54:00:a0:cc:bf' name='VM191' ip='192.168.13.191'/>
			<host mac='52:54:00:a0:cc:c0' name='VM192' ip='192.168.13.192'/>
			<host mac='52:54:00:a0:cc:c1' name='VM193' ip='192.168.13.193'/>
			<host mac='52:54:00:a0:cc:c2' name='VM194' ip='192.168.13.194'/>
			<host mac='52:54:00:a0:cc:c3' name='VM195' ip='192.168.13.195'/>
			<host mac='52:54:00:a0:cc:c4' name='VM196' ip='192.168.13.196'/>
			<host mac='52:54:00:a0:cc:c5' name='VM197' ip='192.168.13.197'/>
			<host mac='52:54:00:a0:cc:c6' name='VM198' ip='192.168.13.198'/>
			<host mac='52:54:00:a0:cc:c7' name='VM199' ip='192.168.13.199'/>
			<host mac='52:54:00:a0:cc:c8' name='VM200' ip='192.168.13.200'/>
			<host mac='52:54:00:a0:cc:c9' name='VM201' ip='192.168.13.201'/>
			<host mac='52:54:00:a0:cc:ca' name='VM202' ip='192.168.13.202'/>
			<host mac='52:54:00:a0:cc:cb' name='VM203' ip='192.168.13.203'/>
			<host mac='52:54:00:a0:cc:cc' name='VM204' ip='192.168.13.204'/>
			<host mac='52:54:00:a0:cc:cd' name='VM205' ip='192.168.13.205'/>
			<host mac='52:54:00:a0:cc:ce' name='VM206' ip='192.168.13.206'/>
			<host mac='52:54:00:a0:cc:cf' name='VM207' ip='192.168.13.207'/>
			<host mac='52:54:00:a0:cc:d0' name='VM208' ip='192.168.13.208'/>
			<host mac='52:54:00:a0:cc:d1' name='VM209' ip='192.168.13.209'/>
			<host mac='52:54:00:a0:cc:d2' name='VM210' ip='192.168.13.210'/>
			<host mac='52:54:00:a0:cc:d3' name='VM211' ip='192.168.13.211'/>
			<host mac='52:54:00:a0:cc:d4' name='VM212' ip='192.168.13.212'/>
			<host mac='52:54:00:a0:cc:d5' name='VM213' ip='192.168.13.213'/>
			<host mac='52:54:00:a0:cc:d6' name='VM214' ip='192.168.13.214'/>
			<host mac='52:54:00:a0:cc:d7' name='VM215' ip='192.168.13.215'/>
			<host mac='52:54:00:a0:cc:d8' name='VM216' ip='192.168.13.216'/>
			<host mac='52:54:00:a0:cc:d9' name='VM217' ip='192.168.13.217'/>
			<host mac='52:54:00:a0:cc:da' name='VM218' ip='192.168.13.218'/>
			<host mac='52:54:00:a0:cc:db' name='VM219' ip='192.168.13.219'/>
			<host mac='52:54:00:a0:cc:dc' name='VM220' ip='192.168.13.220'/>
			<host mac='52:54:00:a0:cc:dd' name='VM221' ip='192.168.13.221'/>
			<host mac='52:54:00:a0:cc:de' name='VM222' ip='192.168.13.222'/>
			<host mac='52:54:00:a0:cc:df' name='VM223' ip='192.168.13.223'/>
			<host mac='52:54:00:a0:cc:e0' name='VM224' ip='192.168.13.224'/>
			<host mac='52:54:00:a0:cc:e1' name='VM225' ip='192.168.13.225'/>
			<host mac='52:54:00:a0:cc:e2' name='VM226' ip='192.168.13.226'/>
			<host mac='52:54:00:a0:cc:e3' name='VM227' ip='192.168.13.227'/>
			<host mac='52:54:00:a0:cc:e4' name='VM228' ip='192.168.13.228'/>
			<host mac='52:54:00:a0:cc:e5' name='VM229' ip='192.168.13.229'/>
			<host mac='52:54:00:a0:cc:e6' name='VM230' ip='192.168.13.230'/>
			<host mac='52:54:00:a0:cc:e7' name='VM231' ip='192.168.13.231'/>
			<host mac='52:54:00:a0:cc:e8' name='VM232' ip='192.168.13.232'/>
			<host mac='52:54:00:a0:cc:e9' name='VM233' ip='192.168.13.233'/>
			<host mac='52:54:00:a0:cc:ea' name='VM234' ip='192.168.13.234'/>
			<host mac='52:54:00:a0:cc:eb' name='VM235' ip='192.168.13.235'/>
			<host mac='52:54:00:a0:cc:ec' name='VM236' ip='192.168.13.236'/>
			<host mac='52:54:00:a0:cc:ed' name='VM237' ip='192.168.13.237'/>
			<host mac='52:54:00:a0:cc:ee' name='VM238' ip='192.168.13.238'/>
			<host mac='52:54:00:a0:cc:ef' name='VM239' ip='192.168.13.239'/>
			<host mac='52:54:00:a0:cc:f0' name='VM240' ip='192.168.13.240'/>
			<host mac='52:54:00:a0:cc:f1' name='VM241' ip='192.168.13.241'/>
			<host mac='52:54:00:a0:cc:f2' name='VM242' ip='192.168.13.242'/>
			<host mac='52:54:00:a0:cc:f3' name='VM243' ip='192.168.13.243'/>
			<host mac='52:54:00:a0:cc:f4' name='VM244' ip='192.168.13.244'/>
			<host mac='52:54:00:a0:cc:f5' name='VM245' ip='192.168.13.245'/>
			<host mac='52:54:00:a0:cc:f6' name='VM246' ip='192.168.13.246'/>
			<host mac='52:54:00:a0:cc:f7' name='VM247' ip='192.168.13.247'/>
			<host mac='52:54:00:a0:cc:f8' name='VM248' ip='192.168.13.248'/>
			<host mac='52:54:00:a0:cc:f9' name='VM249' ip='192.168.13.249'/>
			<host mac='52:54:00:a0:cc:fa' name='VM250' ip='192.168.13.250'/>
			<host mac='52:54:00:a0:cc:fb' name='VM251' ip='192.168.13.251'/>
			<host mac='52:54:00:a0:cc:fc' name='VM252' ip='192.168.13.252'/>
			<host mac='52:54:00:a0:cc:fd' name='VM253' ip='192.168.13.253'/>
			<host mac='52:54:00:a0:cc:fe' name='VM254' ip='192.168.13.254'/>
		</dhcp>
	</ip>
</network>
